<?xml version="1.0" encoding="utf-8"?>
<!DOCTYPE hibernate-mapping PUBLIC "-//Hibernate/Hibernate Mapping DTD 3.0//EN"
"http://hibernate.sourceforge.net/hibernate-mapping-3.0.dtd">
<!-- 
    Mapping file autogenerated by MyEclipse Persistence Tools
-->
<hibernate-mapping>
    <class name="com.nongzi.vo.Admins" table="admins" catalog="nongzi">
        <id name="adminid" type="java.lang.String">
            <column name="adminid" length="32" />
            <generator class="uuid.hex" />
        </id>
        <many-to-one name="role" class="com.nongzi.vo.Role" fetch="select">
            <column name="roleid" length="32" not-null="true" />
        </many-to-one>
        <property name="username" type="java.lang.String">
            <column name="username" length="65535" not-null="true" />
        </property>
        <property name="userpwd" type="java.lang.String">
            <column name="userpwd" length="32" not-null="true" />
        </property>
        <property name="islock" type="java.lang.Double">
            <column name="islock" precision="22" scale="0" not-null="true" />
        </property>
        <property name="adddata" type="java.sql.Timestamp">
            <column name="adddata" length="19" />
        </property>
        <property name="realname" type="java.lang.String">
            <column name="realname" length="180" />
        </property>
    </class>
</hibernate-mapping>
